qai_hub/__init__.py
qai_hub/_cli.py
qai_hub/_version.py
qai_hub/api_status_codes.py
qai_hub/api_utils.py
qai_hub/client.py
qai_hub/hub.py
qai_hub/public_api_pb2.py
qai_hub/public_api_pb2.pyi
qai_hub/public_rest_api.py
qai_hub/py.typed
qai_hub/test/__init__.py
qai_hub/test/test_cli.py
qai_hub/test/test_client.py
qai_hub/test/test_public_rest_api.py
qai_hub/test/test_session.py
qai_hub/test/test_zipped_model.py
qai_hub/util/__init__.py
qai_hub/util/dataset_entries_converters.py
qai_hub/util/job.py
qai_hub/util/session.py
qai_hub/util/zipped_model.py
qai_hub-0.42.0.dist-info/METADATA
qai_hub-0.42.0.dist-info/WHEEL
qai_hub-0.42.0.dist-info/entry_points.txt
qai_hub-0.42.0.dist-info/top_level.txt
qai_hub-0.42.0.dist-info/RECORD
